django_dramatiq_pg/__init__.py
django_dramatiq_pg/admin.py
django_dramatiq_pg/apps.py
django_dramatiq_pg/migrations/0001_initial.py
django_dramatiq_pg/migrations/__init__.py
django_dramatiq_pg/models.py
django_dramatiq_pg/registry.py
django_dramatiq_pg/signals.py
django_dramatiq_pg/worker.py
django_dramatiq_pg-1.3.2.dist-info/WHEEL
django_dramatiq_pg-1.3.2.dist-info/METADATA
django_dramatiq_pg-1.3.2.dist-info/RECORD
