Metadata-Version: 2.1
Name: django-dramatiq-pg
Version: 1.3.2
Summary: Integration of Django with dramatiq-pg
Home-page: https://github.com/uptick/django-dramatiq-pg
License: MIT
Author: Curtis Maloney
Author-email: curtis@tinbrain.net
Requires-Python: >=3.7,<4.0
Classifier: Development Status :: 5 - Production/Stable
Classifier: Framework :: Django
Classifier: Framework :: Django :: 3.0
Classifier: Framework :: Django :: 3.1
Classifier: License :: OSI Approved :: MIT License
Classifier: Programming Language :: Python
Classifier: Programming Language :: Python :: 3
Classifier: Programming Language :: Python :: 3.7
Classifier: Programming Language :: Python :: 3.8
Classifier: Programming Language :: Python :: 3.9
Requires-Dist: django (>=3.1)
Requires-Dist: dramatiq-pg (>=0.9.0)
